tpmsc.py
tpmsc-1.0.0.dist-info/METADATA
tpmsc-1.0.0.dist-info/WHEEL
tpmsc-1.0.0.dist-info/entry_points.txt
tpmsc-1.0.0.dist-info/RECORD
