Metadata-Version: 2.1
Name: tpmsc
Version: 1.0.0
Summary: CLI tool to download music collages from tapmusic.net
License: MIT
Author: atomheartbrother
Author-email: rhnsolomon@gmail.com
Requires-Python: >=3.6,<4.0
Classifier: License :: OSI Approved :: MIT License
Classifier: Programming Language :: Python :: 3
Classifier: Programming Language :: Python :: 3.6
Classifier: Programming Language :: Python :: 3.7
Classifier: Programming Language :: Python :: 3.8
Classifier: Programming Language :: Python :: 3.9
Classifier: Programming Language :: Python :: 3.10
Classifier: Programming Language :: Python :: 3.11
Classifier: Programming Language :: Python :: 3.12
Requires-Dist: pathlib (>=1.0.1,<2.0.0)
Requires-Dist: requests (>=2.28.1,<3.0.0)
